steembit/__init__.py
steembit/constants.py
steembit/steembit.py
steembit/utils.py
steembit-0.0.2.dist-info/LICENSE.txt
steembit-0.0.2.dist-info/METADATA
steembit-0.0.2.dist-info/WHEEL
steembit-0.0.2.dist-info/entry_points.txt
steembit-0.0.2.dist-info/top_level.txt
steembit-0.0.2.dist-info/RECORD
