Metadata-Version: 2.1
Name: steembit
Version: 0.0.2
Summary: Simple CLI tool for Steem users
Home-page: UNKNOWN
Author: Martin Šmíd
Author-email: martin.smid94@seznam.cz
License: MIT
Keywords: steem cli
Platform: UNKNOWN
Classifier: Development Status :: 3 - Alpha
Classifier: Programming Language :: Python :: 3.6
Classifier: License :: OSI Approved :: MIT License
Requires-Dist: Click
Requires-Dist: beem
